{"__v":0,"_id":"525001471e93d5947a000011","items":{"youtube":{"240":{"1528":{"val":1,"data":{"video":"lOORk2gx3Kw","playlist":"","time":0}}}},"target":{"16":{"1472":{"val":1,"data":{}},"1592":{}},"32":{"1448":{}},"40":{"1448":{"val":2,"data":{}}},"72":{"1424":{}},"80":{"1424":{"val":2,"data":{}},"1576":{},"1592":{}},"144":{"1392":{}},"152":{"1392":{"val":1,"data":{}},"1400":{}},"168":{"1392":{"val":1,"data":{}},"1400":{}},"232":{"1416":{"val":2,"data":{}}},"248":{"1424":{}},"272":{"1448":{"val":2,"data":{}}},"280":{"1448":{}},"296":{"1472":{"val":1,"data":{}},"1592":{}}},"switchblock":{"16":{"1584":{}},"248":{"1496":{}},"256":{"1504":{}},"264":{"1480":{}},"272":{"1488":{}},"280":{"1496":{}},"288":{"1504":{},"1584":{}}},"spikeblock":{"16":{"1576":{},"1584":{}},"24":{"1464":{},"1472":{}},"32":{"1464":{}},"40":{"1448":{}},"48":{"1464":{},"1472":{"val":1,"data":{}}},"64":{"1464":{}},"72":{"1464":{},"1472":{"val":1,"data":{}}},"80":{"1464":{},"1472":{"val":1,"data":{}}},"88":{"1448":{}},"120":{"1464":{}},"128":{"1464":{"val":1,"data":{}},"1472":{},"1480":{}},"144":{"1448":{}},"160":{"1456":{},"1480":{}},"168":{"1464":{"val":1,"data":{}},"1496":{}},"176":{"1480":{}},"192":{"1464":{}},"208":{"1464":{"val":1,"data":{}}},"216":{"1456":{},"1480":{}},"224":{"1464":{}},"248":{"1464":{"val":1,"data":{}},"1496":{}},"256":{"1456":{},"1472":{}},"272":{"1464":{}},"288":{"1464":{},"1576":{},"1584":{}}},"sign":{"56":{"1544":{"val":1,"data":{"message":"You'll require the Elemental Keys in order to progress...","name":"sign-0|JacobDaGun"}}}},"platform":{"16":{"1592":{}},"24":{"1520":{}},"264":{"1592":{}}},"goomba":{"24":{"1480":{},"1488":{}},"32":{"1448":{},"1504":{}},"48":{"1448":{},"1488":{"val":1,"data":{}}},"56":{"1488":{}},"80":{"1448":{},"1464":{},"1480":{"val":1,"data":{}},"1544":{}},"88":{"1472":{},"1536":{}},"96":{"1536":{}},"104":{"1448":{},"1536":{}},"120":{"1536":{}},"128":{"1448":{},"1480":{"val":1,"data":{}},"1496":{}},"136":{"1536":{}},"144":{"1456":{}},"152":{"1464":{}},"160":{"1448":{},"1528":{}},"168":{"1480":{"val":1,"data":{}},"1488":{}},"176":{"1480":{},"1488":{},"1520":{}},"184":{"1488":{},"1536":{}},"200":{"1456":{},"1464":{},"1528":{}},"208":{"1456":{},"1480":{"val":1,"data":{}}},"216":{"1472":{},"1528":{},"1536":{}},"224":{"1472":{},"1480":{},"1496":{},"1504":{}},"232":{"1456":{}},"240":{"1472":{},"1488":{}},"248":{"1464":{},"1472":{},"1480":{"val":1,"data":{}}},"256":{"1464":{}},"264":{"1440":{},"1464":{}},"272":{"1464":{},"1504":{}},"288":{"1480":{}}},"fish":{"16":{"1584":{}},"288":{"1584":{}}},"custom":{"80":{},"96":{"1536":{"data":{},"val":"_bphn5fkg9"},"1552":{"data":{},"val":"_z4phnv0uu"}},"112":{},"128":{"1536":{"data":{},"val":"_gf8c7ijiy"},"1552":{"data":{},"val":"_2jlkwrstn"}},"144":{},"160":{"1536":{"data":{},"val":"_9mrs3wccf"},"1552":{"data":{},"val":"_y3ncjmusj"}},"168":{},"176":{},"192":{"1536":{"data":{},"val":"_1gi3ycmgb"},"1552":{"data":{},"val":"_1gi3ycmgb"}},"208":{}},"block":{"16":{"1504":{"val":1,"data":{"frame":1,"flip":{"x":false,"y":false},"user":"JacobDaGun","set":"_g77ztryni"}}},"32":{"1504":{"val":1,"data":{"frame":1,"flip":{"x":false,"y":false},"user":"JacobDaGun","set":"_g77ztryni"}}},"48":{"1504":{"val":1,"data":{"frame":1,"flip":{"x":false,"y":false},"user":"JacobDaGun","set":"_g77ztryni"}}},"64":{"1504":{"val":1,"data":{"frame":1,"flip":{"x":false,"y":false},"user":"JacobDaGun","set":"_g77ztryni"}}},"80":{"1504":{"val":1,"data":{"frame":1,"flip":{"x":false,"y":false},"user":"JacobDaGun","set":"_g77ztryni"}},"1568":{"data":{"flip":{"y":false,"x":false},"frame":5},"val":1}},"96":{"1504":{"val":1,"data":{"frame":1,"flip":{"x":false,"y":false},"user":"JacobDaGun","set":"_g77ztryni"}},"1520":{"data":{"set":"_g77ztryni","user":"JacobDaGun","flip":{"y":false,"x":false},"frame":1},"val":1}},"112":{"1504":{"val":1,"data":{"frame":1,"flip":{"x":false,"y":false},"user":"JacobDaGun","set":"_g77ztryni"}}},"128":{"1504":{"val":1,"data":{"frame":1,"flip":{"x":false,"y":false},"user":"JacobDaGun","set":"_g77ztryni"}},"1520":{"data":{"set":"_g77ztryni","user":"JacobDaGun","flip":{"y":false,"x":false},"frame":1},"val":1}},"144":{"1504":{"val":1,"data":{"frame":1,"flip":{"x":false,"y":false},"user":"JacobDaGun","set":"_g77ztryni"}}},"160":{"1504":{"val":1,"data":{"frame":1,"flip":{"x":false,"y":false},"user":"JacobDaGun","set":"_g77ztryni"}},"1520":{"data":{"set":"_g77ztryni","user":"JacobDaGun","flip":{"y":false,"x":false},"frame":1},"val":1}},"176":{"1504":{"val":1,"data":{"frame":1,"flip":{"x":false,"y":false},"user":"JacobDaGun","set":"_g77ztryni"}}},"192":{"1504":{"val":1,"data":{"frame":1,"flip":{"x":false,"y":false},"user":"JacobDaGun","set":"_g77ztryni"}},"1520":{"data":{"set":"_g77ztryni","user":"JacobDaGun","flip":{"y":false,"x":false},"frame":1},"val":1}},"208":{"1504":{"val":1,"data":{"frame":1,"flip":{"x":false,"y":false},"user":"JacobDaGun","set":"_g77ztryni"}}},"224":{"1504":{"val":1,"data":{"frame":1,"flip":{"x":false,"y":false},"user":"JacobDaGun","set":"_g77ztryni"}}},"240":{"1504":{"val":1,"data":{"frame":5,"flip":{"x":false,"y":false},"user":"JacobDaGun","set":"_g77ztryni"}}},"256":{"1504":{"val":1,"data":{"frame":5,"flip":{"x":false,"y":false},"user":"JacobDaGun","set":"_g77ztryni"}}},"272":{"1504":{"val":1,"data":{"frame":5,"flip":{"x":false,"y":false},"user":"JacobDaGun","set":"_g77ztryni"}}},"288":{"1504":{"val":1,"data":{"frame":1,"flip":{"x":false,"y":false},"user":"JacobDaGun","set":"_g77ztryni"}},"1568":{"data":{"flip":{"y":false,"x":false},"frame":5},"val":1}}},"bit":{"16":{"1472":{},"1480":{},"1504":{"data":{"val":1,"layer":"2"},"val":1},"1512":{"data":{"val":1,"layer":"2"},"val":1}},"24":{"1472":{},"1496":{},"1504":{"data":{"val":1,"layer":"2"},"val":1},"1512":{"data":{"val":1,"layer":"2"},"val":1}},"32":{"1496":{},"1504":{"data":{"val":1,"layer":"2"},"val":1},"1512":{"data":{"val":1,"layer":"2"},"val":1}},"40":{"1496":{},"1504":{"data":{"val":1,"layer":"2"},"val":1},"1512":{"data":{"val":1,"layer":"2"},"val":1}},"48":{"1504":{"data":{"val":1,"layer":"2"},"val":1},"1512":{"data":{"val":1,"layer":"2"},"val":1}},"56":{"1504":{"data":{"val":1,"layer":"2"},"val":1},"1512":{"data":{"val":1,"layer":"2"},"val":1}},"64":{"1504":{"data":{"val":1,"layer":"2"},"val":1},"1512":{"data":{"val":1,"layer":"2"},"val":1},"1528":{},"1536":{}},"72":{"1504":{"data":{"val":1,"layer":"2"},"val":1},"1512":{"data":{"val":1,"layer":"2"},"val":1},"1528":{},"1536":{},"1544":{},"1552":{},"1560":{}},"80":{"1496":{},"1504":{"data":{"val":1,"layer":"2"},"val":1},"1512":{"data":{"val":1,"layer":"2"},"val":1},"1544":{}},"84":{"1572":{}},"88":{"1496":{},"1504":{"data":{"val":1,"layer":"2"},"val":1},"1512":{"data":{"val":1,"layer":"2"},"val":1},"1520":{},"1544":{},"1572":{}},"96":{"1504":{"data":{"val":1,"layer":"2"},"val":1},"1512":{"data":{"val":1,"layer":"2"},"val":1},"1520":{"val":1,"data":{"layer":"2","val":1}},"1528":{"val":1,"data":{"layer":"2","val":1}},"1544":{}},"104":{"1504":{"data":{"val":1,"layer":"2"},"val":1},"1512":{"data":{"val":1,"layer":"2"},"val":1},"1520":{"val":1,"data":{"layer":"2","val":1}},"1528":{"val":1,"data":{"layer":"2","val":1}}},"112":{"1504":{"data":{"val":1,"layer":"2"},"val":1},"1512":{"data":{"val":1,"layer":"2"},"val":1}},"120":{"1504":{"data":{"val":1,"layer":"2"},"val":1},"1512":{"data":{"val":1,"layer":"2"},"val":1}},"128":{"1496":{},"1504":{"data":{"val":1,"layer":"2"},"val":1},"1512":{"data":{"val":1,"layer":"2"},"val":1},"1520":{"val":1,"data":{"layer":"2","val":1}},"1528":{"val":1,"data":{"layer":"2","val":1}}},"136":{"1496":{},"1504":{"data":{"val":1,"layer":"2"},"val":1},"1512":{"data":{"val":1,"layer":"2"},"val":1},"1520":{"val":1,"data":{"layer":"2","val":1}},"1528":{"val":1,"data":{"layer":"2","val":1}}},"144":{"1504":{"data":{"val":1,"layer":"2"},"val":1},"1512":{"data":{"val":1,"layer":"2"},"val":1},"1520":{},"1528":{}},"152":{"1504":{"data":{"val":1,"layer":"2"},"val":1},"1512":{"data":{"val":1,"layer":"2"},"val":1},"1520":{},"1528":{}},"160":{"1504":{"data":{"val":1,"layer":"2"},"val":1},"1512":{"data":{"val":1,"layer":"2"},"val":1},"1520":{"val":1,"data":{"layer":"2","val":1}},"1528":{"val":1,"data":{"layer":"2","val":1}}},"168":{"1496":{},"1504":{"data":{"val":1,"layer":"2"},"val":1},"1512":{"data":{"val":1,"layer":"2"},"val":1},"1520":{"val":1,"data":{"layer":"2","val":1}},"1528":{"val":1,"data":{"layer":"2","val":1}},"1544":{}},"172":{"1548":{}},"176":{"1496":{},"1504":{"data":{"val":1,"layer":"2"},"val":1},"1512":{"data":{"val":1,"layer":"2"},"val":1}},"184":{"1496":{},"1504":{"data":{"val":1,"layer":"2"},"val":1},"1512":{"data":{"val":1,"layer":"2"},"val":1}},"192":{"1344":{"data":{"layer":1},"val":1},"1504":{"data":{"val":1,"layer":"2"},"val":1},"1512":{"data":{"val":1,"layer":"2"},"val":1},"1520":{"val":1,"data":{"layer":"2","val":1}},"1528":{"val":1,"data":{"layer":"2","val":1}}},"200":{"1504":{"data":{"val":1,"layer":"2"},"val":1},"1512":{"data":{"val":1,"layer":"2"},"val":1},"1520":{"val":1,"data":{"layer":"2","val":1}},"1528":{"val":1,"data":{"layer":"2","val":1}}},"208":{"1496":{},"1504":{"data":{"val":1,"layer":"2"},"val":1},"1512":{"data":{"val":1,"layer":"2"},"val":1}},"216":{"1496":{},"1504":{"data":{"val":1,"layer":"2"},"val":1},"1512":{"data":{"val":1,"layer":"2"},"val":1}},"224":{"1496":{},"1504":{"data":{"val":1,"layer":"2"},"val":1},"1512":{"data":{"val":1,"layer":"2"},"val":1}},"232":{"1472":{},"1480":{},"1488":{},"1496":{},"1504":{"data":{"val":1,"layer":"2"},"val":1},"1512":{"data":{"val":1,"layer":"2"},"val":1},"1520":{}},"240":{"1472":{},"1504":{"data":{"val":3,"layer":"2"},"val":3},"1512":{"data":{"val":3,"layer":"2"},"val":3},"1520":{}},"244":{"1516":{}},"248":{"1472":{},"1496":{},"1504":{"data":{"val":8,"layer":"2"},"val":8},"1512":{"data":{"val":3,"layer":"2"},"val":3},"1520":{}},"252":{"1516":{}},"256":{"1472":{},"1496":{},"1504":{"data":{"val":3,"layer":"2"},"val":3},"1512":{"data":{"val":3,"layer":"2"},"val":3},"1520":{}},"260":{"1516":{}},"264":{"1472":{},"1504":{"data":{"val":3,"layer":"2"},"val":3},"1512":{"data":{"val":3,"layer":"2"},"val":3},"1520":{}},"268":{"1516":{}},"272":{"1472":{},"1504":{"data":{"val":8,"layer":"2"},"val":8},"1512":{"data":{"val":3,"layer":"2"},"val":3},"1520":{}},"276":{"1516":{}},"280":{"1472":{},"1504":{"data":{"val":3,"layer":"2"},"val":3},"1512":{"data":{"val":3,"layer":"2"},"val":3},"1516":{},"1520":{}},"288":{"1472":{},"1496":{},"1504":{"data":{"val":1,"layer":"2"},"val":1},"1512":{"data":{"val":1,"layer":"2"},"val":1},"1516":{},"1520":{},"1572":{}},"296":{"1472":{},"1496":{},"1504":{"data":{"val":1,"layer":"2"},"val":1},"1512":{"data":{"val":1,"layer":"2"},"val":1},"1516":{},"1520":{},"1544":{},"1560":{},"1572":{}}}},"leveltype":"3","removeditems":{"bit":{"16":{"1472":1,"1480":1},"24":{"1472":1,"1496":1},"32":{"1496":1},"40":{"1496":1},"64":{"1528":2,"1536":2},"72":{"1528":1,"1536":1,"1544":1,"1552":1,"1560":1},"80":{"1496":1,"1544":1},"84":{"1572":1},"88":{"1496":1,"1520":1,"1544":1,"1572":1},"96":{"1544":1},"128":{"1496":1,"1520":1,"1528":1},"136":{"1496":1,"1520":1,"1528":1},"144":{"1520":1,"1528":1},"152":{"1504":1,"1520":1,"1528":1},"168":{"1496":1,"1544":1},"172":{"1548":1},"176":{"1496":1},"184":{"1496":1},"192":{"1520":1,"1528":1},"200":{"1520":1,"1528":1},"208":{"1496":1},"216":{"1496":1},"224":{"1496":1},"232":{"1472":1,"1480":1,"1488":1,"1496":1,"1504":1,"1512":1,"1520":1},"240":{"1472":1,"1512":1,"1520":1},"244":{"1516":1},"248":{"1472":1,"1496":1,"1504":1,"1512":1,"1520":1},"252":{"1516":1},"256":{"1472":1,"1496":1,"1512":1,"1520":1},"260":{"1516":1},"264":{"1472":1,"1512":1,"1520":1},"268":{"1516":1},"272":{"1472":1,"1504":8,"1512":1,"1520":1},"276":{"1516":1},"280":{"1472":1,"1504":1,"1512":1,"1516":1,"1520":1},"288":{"1472":1,"1496":1,"1512":1,"1516":1,"1520":1,"1572":1},"296":{"1472":1,"1496":1,"1512":1,"1516":1,"1520":1,"1544":1,"1560":2,"1572":1}},"block":{"80":{"1568":5},"240":{"1504":5},"256":{"1504":5},"272":{"1504":5},"288":{"1568":5}},"fish":{"16":{"1584":1},"288":{"1584":1}},"goomba":{"24":{"1480":1,"1488":1},"32":{"1448":1,"1504":1},"48":{"1448":1},"56":{"1488":1},"80":{"1448":1,"1464":1,"1544":1},"88":{"1472":1,"1536":1},"96":{"1536":1},"104":{"1448":1,"1536":1},"120":{"1536":1},"128":{"1448":1,"1496":1},"136":{"1536":1},"144":{"1456":1},"152":{"1464":1},"160":{"1448":1,"1528":1},"168":{"1488":1},"176":{"1480":1,"1488":1,"1520":1},"184":{"1488":1,"1536":1},"200":{"1456":1,"1464":1,"1528":1},"208":{"1456":1},"216":{"1472":1,"1528":1,"1536":1},"224":{"1472":1,"1480":1,"1496":1,"1504":1},"232":{"1456":1},"240":{"1472":1,"1488":1},"248":{"1464":1,"1472":1},"256":{"1464":1},"264":{"1440":1,"1464":1},"272":{"1464":1,"1504":1},"288":{"1480":1}},"platform":{"16":{"1592":1},"24":{"1520":1},"264":{"1592":1}},"sign":{"56":{"1544":1}},"spikeblock":{"16":{"1576":1,"1584":1},"24":{"1464":1,"1472":1},"32":{"1464":1},"40":{"1448":1},"48":{"1464":1},"64":{"1464":1},"72":{"1464":1},"80":{"1464":1},"88":{"1448":1},"120":{"1464":1},"128":{"1464":1,"1472":1,"1480":1},"144":{"1448":1},"160":{"1456":1,"1480":1},"168":{"1496":1},"176":{"1480":1},"192":{"1464":1},"208":{"1464":1},"216":{"1456":1,"1480":1},"224":{"1464":1},"248":{"1464":1,"1496":1},"256":{"1456":1,"1472":1},"272":{"1464":1},"288":{"1464":1,"1576":1,"1584":1}},"switchblock":{"16":{"1584":1},"248":{"1496":1},"256":{"1504":1},"264":{"1480":1},"272":{"1488":1},"280":{"1496":1},"288":{"1504":1,"1584":1}},"target":{"16":{"1592":1},"32":{"1448":1},"72":{"1424":1},"80":{"1576":1,"1592":1},"144":{"1392":1},"152":{"1400":1},"168":{"1392":1,"1400":1},"248":{"1424":1},"272":{"1448":1},"280":{"1448":1},"296":{"1592":1}}},"room":"LevelWater4|JacobDaGun*3","settings":{"title":"The Final Stand"},"username":"JacobDaGun"}